{
  "$schema": "https://json-structure.org/meta/core/v0/#",
  "$id": "https://raw.githubusercontent.com/api-evangelist/amazon-glue/refs/heads/main/json-structure/glue-get-dataflow-graph-response-structure.json",
  "name": "GetDataflowGraphResponse",
  "description": "GetDataflowGraphResponse schema from Amazon Glue API",
  "type": "object",
  "properties": {
    "DagNodes": {
      "allOf": [
        {
          "$ref": "#/components/schemas/DagNodes"
        },
        {
          "description": "A list of the nodes in the resulting DAG."
        }
      ]
    },
    "DagEdges": {
      "allOf": [
        {
          "$ref": "#/components/schemas/DagEdges"
        },
        {
          "description": "A list of the edges in the resulting DAG."
        }
      ]
    }
  }
}